{"examples_index.md":"DGTGAXk2","examples_server_disney-sharp.md":"Jbw2FwCF","examples_server_template.md":"nNhW9kYW","examples_server_tractor-shop.md":"BMwsTEsH","examples_spa_tractor-shop.md":"CaQXzg2x","getting-started_concepts.md":"DgJq864R","getting-started_index.md":"Dp8N4X75","getting-started_server_emulator.md":"BxScPZjz","getting-started_server_environment.md":"C_cDpgka","getting-started_server_mf-service.md":"DMXE4juR","getting-started_server_microfrontend.md":"8QFrip_Z","getting-started_server_publishing.md":"RxDwtI3s","getting-started_server_setup.md":"Cl3ETwaA","getting-started_server_tooling.md":"DB9moNua","getting-started_spa_configuration.md":"CSaKWiZx","getting-started_spa_debugging.md":"CanXq57a","getting-started_spa_dependency-injection.md":"Cyb2fnvs","getting-started_spa_environment.md":"KOEPWXXU","getting-started_spa_extensions.md":"DfJPPU1_","getting-started_spa_http.md":"DsGBV7i1","getting-started_spa_localization.md":"DSdDvhrz","getting-started_spa_microfrontend.md":"D7_9Icae","getting-started_spa_other-components.md":"Dz7-wgd5","getting-started_spa_pages.md":"x7K0bfDr","getting-started_spa_parameters.md":"BkA02hVd","getting-started_spa_pilet-service.md":"C3tmyO3b","getting-started_spa_providers.md":"D7qh_wP1","getting-started_spa_publishing.md":"B8bYBZQi","getting-started_spa_root.md":"CZm-I6C5","getting-started_spa_setup.md":"ofYs9wwO","guides_faq.md":"BFxlpS7L","guides_helpers.md":"B7q0DTNm","guides_index.md":"DDbW6Z8Z","guides_roadmap.md":"DURotdX-","imprint.md":"BHNXAFCt","index.md":"BNDBerek"}
