{"examples_index.md":"CpyXsh7j","examples_server_disney-sharp.md":"CK9zmq3c","examples_server_template.md":"I9JRgDCw","examples_server_tractor-shop.md":"CfuawqEE","examples_spa_tractor-shop.md":"BbPqkd4-","getting-started_concepts.md":"BqhOi9yY","getting-started_index.md":"DLmaI57_","getting-started_server_emulator.md":"DisRKGr2","getting-started_server_environment.md":"CGH89FCQ","getting-started_server_mf-service.md":"D43URsAq","getting-started_server_microfrontend.md":"CDFuBXN0","getting-started_server_publishing.md":"DZ7lIdVi","getting-started_server_setup.md":"WeQRNyk4","getting-started_server_tooling.md":"qH6pL7kY","getting-started_spa_configuration.md":"DWP5FIIs","getting-started_spa_debugging.md":"BMvEeUvM","getting-started_spa_dependency-injection.md":"DOJT0S7L","getting-started_spa_environment.md":"IWvh9DsM","getting-started_spa_extensions.md":"C5IJ4noq","getting-started_spa_http.md":"B21c51f4","getting-started_spa_localization.md":"DgGtNV8f","getting-started_spa_microfrontend.md":"Cru0gUyZ","getting-started_spa_other-components.md":"CQrziccS","getting-started_spa_pages.md":"sqQ_7sAS","getting-started_spa_parameters.md":"d6BycXbg","getting-started_spa_pilet-service.md":"BMfTqWGi","getting-started_spa_providers.md":"BbVI9TEY","getting-started_spa_publishing.md":"C6SJMLvJ","getting-started_spa_root.md":"CMLFr3ma","getting-started_spa_setup.md":"Bu-bydAY","guides_faq.md":"BBdnEuCy","guides_helpers.md":"DUFHEYGQ","guides_index.md":"BzE5IqGH","guides_roadmap.md":"FpdzQehq","imprint.md":"d5Z-7mtr","index.md":"B-RccdPr"}
